<?xml version="1.0"?>
<!--<!DOCTYPE metadata SYSTEM "http://www.esri.com/metadata/esriprof80.dtd">-->
<metadata xml:lang="en"><Esri><MetaID>{E7107A4F-087E-4BE9-90F9-C0077C23E6E4}</MetaID><CreaDate>20160429</CreaDate><CreaTime>11402700</CreaTime><SyncOnce>TRUE</SyncOnce><DataProperties><lineage><Process ToolSource="C:\Program Files (x86)\ArcGIS\ArcToolbox\Toolboxes\Data Management Tools.tbx\AddField" Date="20160429" Time="114027">AddField hexagons_dia02_clip id SHORT # # # # NON_NULLABLE NON_REQUIRED # hexagons_dia02_clip</Process><Process ToolSource="C:\Program Files (x86)\ArcGIS\ArcToolbox\Toolboxes\Data Management Tools.tbx\AddField" Date="20160429" Time="114100">AddField hexagons_dia02_clip cost FLOAT # # # # NON_NULLABLE NON_REQUIRED # hexagons_dia02_clip</Process><Process ToolSource="C:\Program Files (x86)\ArcGIS\ArcToolbox\Toolboxes\Data Management Tools.tbx\AddField" Date="20160429" Time="114134">AddField hexagons_dia02_clip status SHORT # # # # NON_NULLABLE NON_REQUIRED # hexagons_dia02_clip</Process><Process ToolSource="C:\Program Files (x86)\ArcGIS\ArcToolbox\Toolboxes\Data Management Tools.tbx\CalculateField" Date="20160429" Time="114238">CalculateField hexagons_dia02_clip id [FID] VB # hexagons_dia02_clip</Process><Process ToolSource="C:\Program Files (x86)\ArcGIS\ArcToolbox\Toolboxes\Data Management Tools.tbx\CalculateField" Date="20160429" Time="114324">CalculateField hexagons_dia02_clip status 0 VB # hexagons_dia02_clip</Process><Process ToolSource="C:\Program Files (x86)\ArcGIS\ArcToolbox\Toolboxes\Data Management Tools.tbx\CalculateField" Date="20160429" Time="114411">CalculateField hexagons_dia02_clip cost 1.1 VB # hexagons_dia02_clip</Process><Process ToolSource="C:\Program Files (x86)\ArcGIS\ArcToolbox\Toolboxes\Data Management Tools.tbx\DeleteField" Date="20160429" Time="114430">DeleteField hexagons_dia02_clip Unique_ID;Hex_Area hexagons_dia02_clip</Process></lineage></DataProperties></Esri></metadata>
